.dockerignore
MANIFEST.in
README.md
README_docker_compose_setup.md
README_running_locally.md
README_setup_local_mediawiki_and_install_dump.md
RELEASES.md
changelog.rst
cmd.txt
docker-compose-initial-setup.yml
docker-compose-only-mediawiki.yml
docker-compose.yml
mw-post
pyproject.toml
pytest.ini
setup.cfg
setup.py
tox.ini
.vscode/settings.json
docker/Dockerfile.base
docker/JobDispatcher.Dockerfile
docker/Postman.Dockerfile
docker/QServe.Dockerfile
docker/Worker.Dockerfile
docs/Makefile
docs/basics.rst
docs/changelog.rst
docs/collection.rst
docs/commands.rst
docs/conf.py
docs/index.rst
docs/installation.rst
docs/internals.rst
docs/metabook.rst
docs/renderserver.rst
docs/writers.rst
mediawiki/.gitkeep
requirements/base.in
requirements/base.txt
requirements/test.in
requirements/test.txt
sandbox/anywikisampler.py
sandbox/bigswitch.py
sandbox/citeweb.py
sandbox/example_mediawiki_request.json
sandbox/expr.txt
sandbox/multicoll.py
sandbox/mw-serve-stresser.py
sandbox/rclient
sandbox/time-expr.py
sandbox/time-parse.py
src/mwlib/__init__.py
src/mwlib/_expander.re
src/mwlib/_uscan.cc
src/mwlib/_uscan.re
src/mwlib/_version.py
src/mwlib/argv.py
src/mwlib/authors.py
src/mwlib/bookshelf.py
src/mwlib/caller.py
src/mwlib/expander.py
src/mwlib/filequeue.py
src/mwlib/imgmap.py
src/mwlib/infobox_magic.py
src/mwlib/linuxmem.py
src/mwlib/metabook.py
src/mwlib/nshandling.py
src/mwlib/nuwiki.py
src/mwlib/snippets.py
src/mwlib/snippets.txt
src/mwlib/tagext.py
src/mwlib/timeline.py
src/mwlib/wiki.py
src/mwlib/writerbase.py
src/mwlib.egg-info/PKG-INFO
src/mwlib.egg-info/SOURCES.txt
src/mwlib.egg-info/dependency_links.txt
src/mwlib.egg-info/namespace_packages.txt
src/mwlib.egg-info/not-zip-safe
src/mwlib.egg-info/requires.txt
src/mwlib.egg-info/top_level.txt
src/mwlib/apps/__init__.py
src/mwlib/apps/buildzip.py
src/mwlib/apps/buildzip_bak.py
src/mwlib/apps/client.py
src/mwlib/apps/make_nuwiki.py
src/mwlib/apps/render.py
src/mwlib/apps/serve.py
src/mwlib/apps/utils.py
src/mwlib/asynchronous/__init__.py
src/mwlib/command/__init__.py
src/mwlib/command/executor.py
src/mwlib/configuration/__init__.py
src/mwlib/configuration/_conf.py
src/mwlib/configuration/conf.py
src/mwlib/consts/__init__.py
src/mwlib/consts/urls.py
