Metadata-Version: 2.1
Name: mwlib
Version: 0.17.0.post1
Summary: UNKNOWN
Home-page: UNKNOWN
License: UNKNOWN
Platform: UNKNOWN
